ip_address_classifier/__init__.py
ip_address_classifier/__main__.py
ip_address_classifier-0.1.5.dist-info/LICENSE
ip_address_classifier-0.1.5.dist-info/METADATA
ip_address_classifier-0.1.5.dist-info/WHEEL
ip_address_classifier-0.1.5.dist-info/entry_points.txt
ip_address_classifier-0.1.5.dist-info/RECORD
