Metadata-Version: 2.1
Name: ip-address-classifier
Version: 0.1.5
Summary: A CLI tool that classifies IPv4 addresses
Author: DavidTJGriffin
Author-email: david.dtjg2001@gmail.com
Requires-Python: >=3.12,<4.0
Classifier: License :: OSI Approved :: MIT License
Classifier: Programming Language :: Python :: 3
Classifier: Programming Language :: Python :: 3.12
